squared/__init__.py
squared/__init__.pyi
squared/__main__.py
squared/cli.py
squared/lazy.py
squared/py.typed
squared/token.py
squared/app/__init__.py
squared/app/game/__init__.py
squared/app/game/main.py
squared/app/game/sprites/__init__.py
squared/app/game/sprites/player.py
squared/app/net/__init__.py
squared/app/net/callbacks.py
squared/app/net/client.py
squared/app/net/filters.py
squared/app/net/packet.py
squared/app/net/server.py
squared/modules/__init__.py
squared/modules/ansi.py
squared/modules/log.py
squared/modules/metadata.py
squared/modules/network.py
squared/modules/parsing/__init__.py
squared/modules/parsing/parents.py
squared/modules/parsing/parsers/__init__.py
squared/modules/parsing/parsers/main.py
squared/parsers/__init__.py
squared/parsers/main.py
squared/parsers/types.py
squared-1.0.1.dist-info/licenses/LICENSE
squared-1.0.1.dist-info/METADATA
squared-1.0.1.dist-info/WHEEL
squared-1.0.1.dist-info/entry_points.txt
squared-1.0.1.dist-info/top_level.txt
squared-1.0.1.dist-info/RECORD
